LICENSE
MANIFEST.in
README.rst
dev_requirements.txt
requirements.txt
setup.py
django_shareddb.egg-info/PKG-INFO
django_shareddb.egg-info/SOURCES.txt
django_shareddb.egg-info/dependency_links.txt
django_shareddb.egg-info/requires.txt
django_shareddb.egg-info/top_level.txt
shareddb/__init__.py
shareddb/compat.py
shareddb/testcase.py
shareddb/threlegate.py
shareddb/backends/__init__.py
shareddb/backends/shareddb/__init__.py
shareddb/backends/shareddb/base.py
tests/__init__.py
tests/test_shareddb.py
tests/testapp/__init__.py
tests/testapp/models.py
tests/testapp/urls.py
tests/testapp/views.py