Metadata-Version: 1.1
Name: django-shareddb
Version: 0.1.2
Summary: Shared database connections for multi-threaded Django test setups.
Home-page: https://github.com/rbarrois/django-shareddb/
Author: Raphaël Barrois
Author-email: raphael.barrois+shareddb@polytechnique.org
License: BSD
Download-URL: https://pypi.python.org/pypi/django-shareddb/
Keywords: django,liveserver,shared connection
Platform: UNKNOWN
Classifier: Development Status :: 4 - Beta
Classifier: Framework :: Django
Classifier: Intended Audience :: Developers
Classifier: License :: OSI Approved :: BSD License
Classifier: Topic :: Software Development :: Libraries :: Python Modules
Classifier: Operating System :: OS Independent
Classifier: Programming Language :: Python
Classifier: Programming Language :: Python :: 2
Classifier: Programming Language :: Python :: 2.7
Classifier: Programming Language :: Python :: 3
Classifier: Programming Language :: Python :: 3.2
Classifier: Programming Language :: Python :: 3.3
